{
    "plugins": [
        "-search",
        "highlight",
        "-hints",
        "-theme-default"
    ],
    "pluginsConfig": {
        "sharing": {
            "facebook": true,
            "twitter": true,
            "google": true,
            "weibo": false,
            "instapaper": false,
            "vk": false,
            "all": "facebook,google,twitter"
        }
    },
    "author": "changkejun",
    "title": "efw help document",
    "links": {
        "sidebar": {
            "Home": "http://www.escco.co.jp"
        }
    },
    "description": "More easier to coding with JavaScript."
}